TransferBackup/__init__.py
TransferBackup/__main__.py
TransferBackup/transfer_backup.py
TransferBackup-0.2.0.dist-info/LICENSE
TransferBackup-0.2.0.dist-info/METADATA
TransferBackup-0.2.0.dist-info/WHEEL
TransferBackup-0.2.0.dist-info/entry_points.txt
TransferBackup-0.2.0.dist-info/top_level.txt
TransferBackup-0.2.0.dist-info/RECORD
