Metadata-Version: 2.1
Name: TransferBackup
Version: 0.2.0
Summary: Copy ABB RAPID backup to customized git folder
Home-page: https://github.com/bonnybabukachappilly/TransferBackup
Author: Bonny Babu
Author-email: Bonny Babu <bonnybabukachappilly@gmail.com>
Maintainer-email: Bonny Babu <bonnybabukachappilly@gmail.com>
License: GNU GENERAL PUBLIC LICENSE
Project-URL: Homepage, https://github.com/bonnybabukachappilly/TransferBackup
Keywords: python,rapid,abb
Classifier: Programming Language :: Python :: 3
Classifier: Programming Language :: Python :: 3.8
Classifier: License :: OSI Approved :: GNU General Public License v3 (GPLv3)
Classifier: Operating System :: Unix
Requires-Python: >=3.8
License-File: LICENSE
Provides-Extra: dev
Requires-Dist: flake8 ; extra == 'dev'
Requires-Dist: tox ; extra == 'dev'
Requires-Dist: mypy ; extra == 'dev'
Requires-Dist: check-manifest ; extra == 'dev'
Provides-Extra: test
Requires-Dist: pytest ; extra == 'test'
Requires-Dist: pytest-cov ; extra == 'test'
Requires-Dist: coverage ; extra == 'test'
